.flake8
.gitignore
.pre-commit-config.yaml
LICENSE.txt
MANIFEST.in
README.md
pyproject.toml
requirements.txt
setup.py
.github/workflows/python-lint.yml
.github/workflows/python-publish.yml
examples/Analyse/decoder.ipynb
examples/Analyse/example_data.txt
examples/Nano-Phyling/nanophyling.ipynb
examples/Phyling API/Phyling python lib/api.ipynb
examples/Phyling API/Phyling python lib/realtime.ipynb
examples/Phyling API/RAW API examples/minimal_apikey.html
examples/Phyling API/RAW API examples/minimal_oauth.py
examples/Phyling API/RAW API examples/realtime.html
examples/Phyling API/RAW API examples/requirement.txt
examples/Phyling API/RAW API examples/single-device.html
phyling/__init__.py
phyling/phyling_utils.py
phyling.egg-info/PKG-INFO
phyling.egg-info/SOURCES.txt
phyling.egg-info/dependency_links.txt
phyling.egg-info/requires.txt
phyling.egg-info/top_level.txt
phyling/api/__init__.py
phyling/api/api.py
phyling/api/phylingSocket.py
phyling/api/realtime.py
phyling/api/record.py
phyling/api/user.py
phyling/api/utils.py
phyling/ble/nanophyling.py
phyling/decoder/__init__.py
phyling/decoder/calibration_use.py
phyling/decoder/decoder.py
phyling/decoder/decoder_utils.c
phyling/decoder/decoder_utils.pyx
tests/__init__.py
tests/test_base.py