Metadata-Version: 2.4
Name: phyling
Version: 7.0.1b5
Summary: Phyling public package
License: MIT License
Project-URL: Homepage, https://github.com/phyling-sport/phyling
License-File: LICENSE.txt
Requires-Dist: numpy<3,>=1.24.4
Dynamic: license-file
